Metadata-Version: 2.1
Name: pidevdistv2
Version: 1.0.0
Summary: A multi purpose package mainly for bots.
Home-page: https://github.com/majajanito/pidevdistv2
Author: Majajanieto
Author-email: majajanitor@blacked.gay
License: MIT
